{
  "rates": [
    {
      "type": "delivery",
      "provider": "DoorDash",
      "serviceType": "Delivery",
      "serviceId": "delivery",
      "deliveryWindowId": "1",
      "deliveryWindows": null,
      "requestedPickupTime": 1655830800000,
      "requestedPickupTimeEnds": null,
      "requestedDropoffTime": null,
      "requestedDropoffTimeEnds": 1655841600000,
      "estimatedPickupTime": 1655830800000,
      "estimatedPickupTimeStarts": 1655830800000,
      "estimatedPickupTimeEnds": null,
      "estimatedDeliveryTime": 1655832987000,
      "estimatedDeliveryTimeStarts": null,
      "estimatedDeliveryTimeEnds": 1655832987000,
      "expires": null,
      "currencyCode": "USD",
      "currency": null,
      "amount": 2076,
      "fee": 2076,
      "chargeDetails": null,
      "ruleApplied": true,
      "noEstimate": false,
      "orderType": null,
      "supportsAlternateLocation": false,
      "code": null,
      "tags": [],
      "storeExternalId": "0001"
    },
    {
      "type": null,
      "provider": "UPS Shipping",
      "serviceType": "Ground",
      "serviceId": null,
      "deliveryWindowId": null,
      "deliveryWindows": null,
      "requestedPickupTime": 1655830800000,
      "requestedPickupTimeEnds": null,
      "requestedDropoffTime": null,
      "requestedDropoffTimeEnds": 1655841600000,
      "estimatedPickupTime": null,
      "estimatedPickupTimeStarts": null,
      "estimatedPickupTimeEnds": null,
      "estimatedDeliveryTime": null,
      "estimatedDeliveryTimeStarts": null,
      "estimatedDeliveryTimeEnds": null,
      "expires": null,
      "currencyCode": "USD",
      "currency": "cents",
      "amount": 1898,
      "fee": null,
      "chargeDetails": [],
      "ruleApplied": false,
      "noEstimate": false,
      "orderType": null,
      "supportsAlternateLocation": false,
      "code": null,
      "tags": [],
      "storeExternalId": "0001"
    },
    {
      "type": "delivery",
      "provider": "Roadie",
      "serviceType": "Delivery",
      "serviceId": "delivery",
      "deliveryWindowId": null,
      "deliveryWindows": null,
      "requestedPickupTime": 1655830800000,
      "requestedPickupTimeEnds": null,
      "requestedDropoffTime": null,
      "requestedDropoffTimeEnds": 1655841600000,
      "estimatedPickupTime": 1655824804000,
      "estimatedPickupTimeStarts": null,
      "estimatedPickupTimeEnds": null,
      "estimatedDeliveryTime": 1655824804000,
      "estimatedDeliveryTimeStarts": null,
      "estimatedDeliveryTimeEnds": 1655832004000,
      "expires": null,
      "currencyCode": "USD",
      "currency": "cents",
      "amount": 1462,
      "fee": null,
      "chargeDetails": null,
      "ruleApplied": false,
      "noEstimate": false,
      "orderType": null,
      "supportsAlternateLocation": false,
      "code": null,
      "tags": [],
      "storeExternalId": "0001"
    }
  ],
  "errors": [],
  "rateId": "62b1e1682810e724d36595ab"
}
